edlm/__init__.py
edlm/__main__.py
edlm/cli.py
edlm/config.py
edlm/convert/__init__.py
edlm/convert/_check_for_unused_images.py
edlm/convert/_context.py
edlm/convert/_exc.py
edlm/convert/_get_includes.py
edlm/convert/_get_index.py
edlm/convert/_get_media_folders.py
edlm/convert/_get_settings.py
edlm/convert/_get_template.py
edlm/convert/_make_pdf.py
edlm/convert/_pdf_info.py
edlm/convert/_settings.py
edlm/convert/_temp_folder.py
edlm/convert/_preprocessor/__init__.py
edlm/convert/_preprocessor/_latex/__init__.py
edlm/convert/_preprocessor/_latex/_abstract.py
edlm/convert/_preprocessor/_latex/_empty_page.py
edlm/convert/_preprocessor/_latex/_title_page.py
edlm/convert/_preprocessor/_markdown/__init__.py
edlm/convert/_preprocessor/_markdown/_aliases.py
edlm/convert/_preprocessor/_markdown/_hyperlinks.py
edlm/convert/_preprocessor/_markdown/_images.py
edlm/convert/_preprocessor/_markdown/_include.py
edlm/convert/_preprocessor/_markdown/_references.py
edlm/external_tools/__init__.py
edlm/external_tools/base.py
edlm/external_tools/miktext/__init__.py
edlm/external_tools/miktext/_miktext.py
edlm/external_tools/pandoc/__init__.py
edlm/external_tools/pandoc/_pandoc.py
edlm-0.1.9.dist-info/DESCRIPTION.rst
edlm-0.1.9.dist-info/METADATA
edlm-0.1.9.dist-info/RECORD
edlm-0.1.9.dist-info/WHEEL
edlm-0.1.9.dist-info/entry_points.txt
edlm-0.1.9.dist-info/metadata.json
edlm-0.1.9.dist-info/top_level.txt
