Metadata-Version: 2.0
Name: edlm
Version: 0.1.9
Summary: UNKNOWN
Home-page: UNKNOWN
Author: UNKNOWN
Author-email: UNKNOWN
License: MIT
Platform: UNKNOWN
Classifier: Development Status :: 2 - Pre-Alpha
Classifier: Environment :: Console
Classifier: Environment :: Win32 (MS Windows)
Classifier: Intended Audience :: End Users/Desktop
Classifier: Natural Language :: English
Classifier: Operating System :: Microsoft :: Windows :: Windows 7
Classifier: Operating System :: Microsoft :: Windows :: Windows 8
Classifier: Operating System :: Microsoft :: Windows :: Windows 8.1
Classifier: Operating System :: Microsoft :: Windows :: Windows 10
Classifier: License :: OSI Approved :: MIT License
Classifier: Programming Language :: Python :: 3.6
Classifier: Programming Language :: Python :: 3.7
Classifier: Topic :: Documentation
Classifier: Topic :: Text Processing
Classifier: Topic :: Text Processing :: Markup
Classifier: Topic :: Text Processing :: Markup :: LaTeX
Classifier: Topic :: Utilities
Requires-Python: >=3.6
Requires-Dist: certifi (==2018.1.18)
Requires-Dist: chardet (==3.0.4)
Requires-Dist: click (==6.7)
Requires-Dist: click-log (==0.2.1)
Requires-Dist: configobj (==5.0.6)
Requires-Dist: delegator.py (==0.0.14)
Requires-Dist: easyprocess (==0.2.3)
Requires-Dist: elib (==0.1.50)
Requires-Dist: everett (==0.9)
Requires-Dist: gtts (==1.2.2)
Requires-Dist: gtts-token (==1.1.1)
Requires-Dist: idna (==2.6)
Requires-Dist: jinja2 (==2.10)
Requires-Dist: markupsafe (==1.0)
Requires-Dist: patool (==1.12)
Requires-Dist: pdfrw (==0.4)
Requires-Dist: pexpect (==4.4.0)
Requires-Dist: ptyprocess (==0.5.2)
Requires-Dist: pyunpack (==0.1.2)
Requires-Dist: pyyaml (==3.12)
Requires-Dist: requests (==2.18.4)
Requires-Dist: six (==1.11.0)
Requires-Dist: tqdm (==4.19.5)
Requires-Dist: urllib3 (==1.22)
